color_spreadsheet/__init__.py
color_spreadsheet/__version__.py
color_spreadsheet/classifier.py
color_spreadsheet/cli.py
color_spreadsheet/core.py
color_spreadsheet/py.typed
color_spreadsheet/reporter.py
color_spreadsheet/colorways/__init__.py
color_spreadsheet/colorways/base.py
color_spreadsheet/colorways/registry.py
color_spreadsheet/colorways/standard_financial.py
color_spreadsheet-0.1.1.dist-info/METADATA
color_spreadsheet-0.1.1.dist-info/WHEEL
color_spreadsheet-0.1.1.dist-info/entry_points.txt
color_spreadsheet-0.1.1.dist-info/licenses/LICENSE.txt
color_spreadsheet-0.1.1.dist-info/RECORD
