Metadata-Version: 2.4
Name: color-spreadsheet
Version: 0.1.1
Summary: Apply color coding to Excel spreadsheet cells based on content type
Author-email: Max Shron <max@shron.net>
License-File: LICENSE.txt
Requires-Python: >=3.9
Requires-Dist: openpyxl
